setup.py
MyFirstPythonPYPI.egg-info/PKG-INFO
MyFirstPythonPYPI.egg-info/SOURCES.txt
MyFirstPythonPYPI.egg-info/dependency_links.txt
MyFirstPythonPYPI.egg-info/top_level.txt
MyFirstPythonPackage/FirstPythonFile.py
MyFirstPythonPackage/MyThirdPythonFile.py
MyFirstPythonPackage/__init__.py