Metadata-Version: 1.0
Name: MyFirstPythonPYPI
Version: 1.0.0.2
Summary: This is Demo Project for PYPI.
Home-page: UNKNOWN
Author: Divya Das
Author-email: Divyajyotidas15@gmail.com
License: Divya-Das_License
Platform: UNKNOWN
